<?xml version="1.0" encoding="UTF-8" standalone="yes"?>
<xdr:wsDr xmlns:xdr="http://schemas.openxmlformats.org/drawingml/2006/spreadsheetDrawing" xmlns:a="http://schemas.openxmlformats.org/drawingml/2006/main"><xdr:twoCellAnchor editAs="oneCell"><xdr:from><xdr:col>0</xdr:col><xdr:colOff>45720</xdr:colOff><xdr:row>0</xdr:row><xdr:rowOff>30480</xdr:rowOff></xdr:from><xdr:to><xdr:col>0</xdr:col><xdr:colOff>1783080</xdr:colOff><xdr:row>3</xdr:row><xdr:rowOff>6773</xdr:rowOff></xdr:to><xdr:pic><xdr:nvPicPr><xdr:cNvPr id="3" name="Picture 2"><a:extLst><a:ext uri="{FF2B5EF4-FFF2-40B4-BE49-F238E27FC236}"><a16:creationId xmlns:a16="http://schemas.microsoft.com/office/drawing/2014/main" id="{EA707593-3CC7-4523-A49F-8622DE85E1A1}"/></a:ext></a:extLst></xdr:cNvPr><xdr:cNvPicPr><a:picLocks noChangeAspect="1"/></xdr:cNvPicPr></xdr:nvPicPr><xdr:blipFill><a:blip xmlns:r="http://schemas.openxmlformats.org/officeDocument/2006/relationships" r:embed="rId1"/><a:stretch><a:fillRect/></a:stretch></xdr:blipFill><xdr:spPr><a:xfrm><a:off x="45720" y="30480"/><a:ext cx="1737360" cy="524933"/></a:xfrm><a:prstGeom prst="rect"><a:avLst/></a:prstGeom></xdr:spPr></xdr:pic><xdr:clientData/></xdr:twoCellAnchor></xdr:wsDr>